stickergithook/__init__.py
stickergithook/cat1.txt
stickergithook/cat2.txt
stickergithook/main.py
stickergithook/runsticker.py
stickergithook-0.1.1.dist-info/METADATA
stickergithook-0.1.1.dist-info/WHEEL
stickergithook-0.1.1.dist-info/entry_points.txt
stickergithook-0.1.1.dist-info/RECORD
